{"country_code":"RO","name":"Romania","timezones":["Europe\/Bucharest"],"location":{"lat":46,"lng":25},"google_calendar":[{"locale":"en","calendar":"en.romanian#holiday@group.v.calendar.google.com","years":[{"year":2019,"holidays":[{"date":"2019-01-01","name":"New Year's Day"},{"date":"2019-01-02","name":"Day after New Year's Day"},{"date":"2019-01-24","name":"Unification Day"},{"date":"2019-02-19","name":"Constantin Brancusi Day"},{"date":"2019-02-24","name":"Dragobete"},{"date":"2019-03-01","name":"M\u0103r\u021bi\u0219or"},{"date":"2019-03-08","name":"International Women's Day"},{"date":"2019-04-26","name":"Orthodox Good Friday"},{"date":"2019-04-28","name":"Orthodox Easter Day"},{"date":"2019-04-29","name":"Orthodox Easter Monday"},{"date":"2019-05-01","name":"Labor Day \/ May Day"},{"date":"2019-05-05","name":"Mother's Day"},{"date":"2019-05-10","name":"Monarchy Day"},{"date":"2019-05-12","name":"Father's Day"},{"date":"2019-06-01","name":"Children's Day"},{"date":"2019-06-06","name":"Orthodox Ascension Day"},{"date":"2019-06-16","name":"Orthodox Pentecost"},{"date":"2019-06-17","name":"Orthodox Pentecost Monday"},{"date":"2019-06-26","name":"Flag Day"},{"date":"2019-07-29","name":"National Anthem Day"},{"date":"2019-08-15","name":"St Mary's Day"},{"date":"2019-10-31","name":"Halloween"},{"date":"2019-11-30","name":"St Andrew's Day"},{"date":"2019-12-01","name":"National holiday"},{"date":"2019-12-08","name":"Constitution Day"},{"date":"2019-12-24","name":"Christmas Eve"},{"date":"2019-12-25","name":"Christmas Day"},{"date":"2019-12-26","name":"Second day of Christmas"},{"date":"2019-12-31","name":"New Year's Eve"},{"date":"2019-04-30","name":"Public holiday"},{"date":"2019-08-16","name":"St Mary's Day Holiday"}]},{"year":2020,"holidays":[{"date":"2020-01-01","name":"New Year's Day"},{"date":"2020-01-02","name":"Day after New Year's Day"},{"date":"2020-01-24","name":"Unification Day"},{"date":"2020-02-19","name":"Constantin Brancusi Day"},{"date":"2020-02-24","name":"Dragobete"},{"date":"2020-03-01","name":"M\u0103r\u021bi\u0219or"},{"date":"2020-03-08","name":"International Women's Day"},{"date":"2020-04-17","name":"Orthodox Good Friday"},{"date":"2020-04-19","name":"Orthodox Easter Day"},{"date":"2020-04-20","name":"Orthodox Easter Monday"},{"date":"2020-05-01","name":"Labor Day \/ May Day"},{"date":"2020-05-03","name":"Mother's Day"},{"date":"2020-05-10","name":"Father's Day"},{"date":"2020-05-10","name":"Monarchy Day"},{"date":"2020-05-28","name":"Orthodox Ascension Day"},{"date":"2020-06-01","name":"Children's Day"},{"date":"2020-06-07","name":"Orthodox Pentecost"},{"date":"2020-06-08","name":"Orthodox Pentecost Monday"},{"date":"2020-06-26","name":"Flag Day"},{"date":"2020-07-29","name":"National Anthem Day"},{"date":"2020-08-15","name":"St Mary's Day"},{"date":"2020-10-31","name":"Halloween"},{"date":"2020-11-30","name":"St Andrew's Day"},{"date":"2020-12-01","name":"National holiday"},{"date":"2020-12-08","name":"Constitution Day"},{"date":"2020-12-24","name":"Christmas Eve"},{"date":"2020-12-25","name":"Christmas Day"},{"date":"2020-12-26","name":"Second day of Christmas"},{"date":"2020-12-31","name":"New Year's Eve"}]},{"year":2021,"holidays":[{"date":"2021-01-01","name":"New Year's Day"},{"date":"2021-01-02","name":"Day after New Year's Day"},{"date":"2021-01-24","name":"Unification Day"},{"date":"2021-02-19","name":"Constantin Brancusi Day"},{"date":"2021-02-24","name":"Dragobete"},{"date":"2021-03-01","name":"M\u0103r\u021bi\u0219or"},{"date":"2021-03-08","name":"International Women's Day"},{"date":"2021-04-30","name":"Orthodox Good Friday"},{"date":"2021-05-01","name":"Labor Day \/ May Day"},{"date":"2021-05-02","name":"Orthodox Easter Day"},{"date":"2021-05-02","name":"Mother's Day"},{"date":"2021-05-03","name":"Orthodox Easter Monday"},{"date":"2021-05-09","name":"Father's Day"},{"date":"2021-05-10","name":"Monarchy Day"},{"date":"2021-06-01","name":"Children's Day"},{"date":"2021-06-10","name":"Orthodox Ascension Day"},{"date":"2021-06-20","name":"Orthodox Pentecost"},{"date":"2021-06-21","name":"Orthodox Pentecost Monday"},{"date":"2021-06-26","name":"Flag Day"},{"date":"2021-07-29","name":"National Anthem Day"},{"date":"2021-08-15","name":"St Mary's Day"},{"date":"2021-10-31","name":"Halloween"},{"date":"2021-11-30","name":"St Andrew's Day"},{"date":"2021-12-01","name":"National holiday"},{"date":"2021-12-08","name":"Constitution Day"},{"date":"2021-12-24","name":"Christmas Eve"},{"date":"2021-12-25","name":"Christmas Day"},{"date":"2021-12-26","name":"Second day of Christmas"},{"date":"2021-12-31","name":"New Year's Eve"}]}]}]}