{"country_code":"FM","name":"Micronesia","timezones":["Pacific\/Chuuk","Pacific\/Pohnpei","Pacific\/Kosrae"],"location":{"lat":6.91666666,"lng":158.25},"google_calendar":[{"locale":"en","calendar":"en.fm#holiday@group.v.calendar.google.com","years":[{"year":2019,"holidays":[{"date":"2019-01-01","name":"New Year's Day"},{"date":"2019-05-10","name":"Constitution Day"},{"date":"2019-10-24","name":"United Nations Day"},{"date":"2019-11-03","name":"Independence Day"},{"date":"2019-11-11","name":"Veterans of Foreign Wars Day"},{"date":"2019-12-25","name":"Christmas Day"},{"date":"2019-11-04","name":"Independence Day observed"}]},{"year":2020,"holidays":[{"date":"2020-01-01","name":"New Year's Day"},{"date":"2020-05-10","name":"Constitution Day"},{"date":"2020-10-24","name":"United Nations Day"},{"date":"2020-11-03","name":"Independence Day"},{"date":"2020-11-11","name":"Veterans of Foreign Wars Day"},{"date":"2020-12-25","name":"Christmas Day"},{"date":"2020-05-11","name":"Constitution Day observed"},{"date":"2020-10-23","name":"United Nations Day observed"}]},{"year":2021,"holidays":[{"date":"2021-01-01","name":"New Year's Day"},{"date":"2021-05-10","name":"Constitution Day"},{"date":"2021-10-24","name":"United Nations Day"},{"date":"2021-11-03","name":"Independence Day"},{"date":"2021-11-11","name":"Veterans of Foreign Wars Day"},{"date":"2021-12-25","name":"Christmas Day"},{"date":"2021-10-25","name":"United Nations Day observed"},{"date":"2021-12-24","name":"Christmas Day observed"},{"date":"2021-12-31","name":"New Year's Day observed"}]}]}]}