{"country_code":"HR","name":"Croatia","timezones":["Europe\/Zagreb"],"location":{"lat":45.16666666,"lng":15.5},"google_calendar":[{"locale":"en","calendar":"en.croatian#holiday@group.v.calendar.google.com","years":[{"year":2019,"holidays":[{"date":"2019-01-01","name":"New Year's Day"},{"date":"2019-01-06","name":"Epiphany"},{"date":"2019-04-22","name":"Easter Monday"},{"date":"2019-05-01","name":"Labor Day \/ May Day"},{"date":"2019-06-20","name":"Corpus Christi"},{"date":"2019-06-22","name":"Day of Antifascist Struggle"},{"date":"2019-06-25","name":"Statehood Day"},{"date":"2019-08-05","name":"Homeland Thanksgiving Day"},{"date":"2019-08-15","name":"Assumption of Mary"},{"date":"2019-10-08","name":"Independence Day"},{"date":"2019-11-01","name":"All Saints' Day"},{"date":"2019-12-25","name":"Christmas Day"},{"date":"2019-12-26","name":"St Stephen's Day"},{"date":"2019-01-07","name":"Orthodox Christmas Day"},{"date":"2019-06-05","name":"Ramadan Bayram"},{"date":"2019-09-30","name":"Rosh Hashana"},{"date":"2019-10-09","name":"Yom Kippur"},{"date":"2019-08-11","name":"Kurban Bayram"},{"date":"2019-04-21","name":"Easter Sunday"}]},{"year":2020,"holidays":[{"date":"2020-01-01","name":"New Year's Day"},{"date":"2020-01-06","name":"Epiphany"},{"date":"2020-04-13","name":"Easter Monday"},{"date":"2020-05-01","name":"Labor Day \/ May Day"},{"date":"2020-06-11","name":"Corpus Christi"},{"date":"2020-06-22","name":"Day of Antifascist Struggle"},{"date":"2020-08-05","name":"Homeland Thanksgiving Day"},{"date":"2020-08-15","name":"Assumption of Mary"},{"date":"2020-11-01","name":"All Saints' Day"},{"date":"2020-12-25","name":"Christmas Day"},{"date":"2020-12-26","name":"St Stephen's Day"},{"date":"2020-04-12","name":"Easter Sunday"},{"date":"2020-01-07","name":"Orthodox Christmas Day"},{"date":"2020-05-24","name":"Ramadan Bayram"},{"date":"2020-07-31","name":"Kurban Bayram"},{"date":"2020-09-19","name":"Rosh Hashana"},{"date":"2020-09-28","name":"Yom Kippur"},{"date":"2020-05-30","name":"Statehood Day"},{"date":"2020-06-25","name":"Independence Day"},{"date":"2020-11-18","name":"Remembrance Day"}]},{"year":2021,"holidays":[{"date":"2021-01-01","name":"New Year's Day"},{"date":"2021-01-06","name":"Epiphany"},{"date":"2021-04-05","name":"Easter Monday"},{"date":"2021-05-01","name":"Labor Day \/ May Day"},{"date":"2021-06-03","name":"Corpus Christi"},{"date":"2021-06-22","name":"Day of Antifascist Struggle"},{"date":"2021-08-05","name":"Homeland Thanksgiving Day"},{"date":"2021-08-15","name":"Assumption of Mary"},{"date":"2021-11-01","name":"All Saints' Day"},{"date":"2021-12-25","name":"Christmas Day"},{"date":"2021-12-26","name":"St Stephen's Day"},{"date":"2021-04-04","name":"Easter Sunday"},{"date":"2021-01-07","name":"Orthodox Christmas Day"},{"date":"2021-07-20","name":"Kurban Bayram"},{"date":"2021-09-07","name":"Rosh Hashana"},{"date":"2021-09-16","name":"Yom Kippur"},{"date":"2021-05-13","name":"Ramadan Bayram"},{"date":"2021-05-30","name":"Statehood Day"},{"date":"2021-06-25","name":"Independence Day"},{"date":"2021-11-18","name":"Remembrance Day"}]}]}]}